cosmicdb/__init__.py
cosmicdb/admin.py
cosmicdb/forms.py
cosmicdb/models.py
cosmicdb/settings.py
cosmicdb/tables.py
cosmicdb/urls.py
cosmicdb/views.py
cosmicdb/__pycache__/__init__.cpython-38.pyc
cosmicdb/__pycache__/admin.cpython-38.pyc
cosmicdb/__pycache__/forms.cpython-38.pyc
cosmicdb/__pycache__/models.cpython-38.pyc
cosmicdb/__pycache__/settings.cpython-38.pyc
cosmicdb/__pycache__/tables.cpython-38.pyc
cosmicdb/__pycache__/urls.cpython-38.pyc
cosmicdb/__pycache__/views.cpython-38.pyc
cosmicdb/migrations/0001_initial.py
cosmicdb/migrations/__init__.py
cosmicdb/migrations/__pycache__/0001_initial.cpython-38.pyc
cosmicdb/migrations/__pycache__/__init__.cpython-38.pyc
cosmicdb/static/admin/js/jquery.init.js
cosmicdb/static/cosmicdb/adminlte/bootstrap/css/bootstrap-theme.css
cosmicdb/static/cosmicdb/adminlte/bootstrap/css/bootstrap-theme.css.map
cosmicdb/static/cosmicdb/adminlte/bootstrap/css/bootstrap-theme.min.css
cosmicdb/static/cosmicdb/adminlte/bootstrap/css/bootstrap-theme.min.css.map
cosmicdb/static/cosmicdb/adminlte/bootstrap/css/bootstrap.css
cosmicdb/static/cosmicdb/adminlte/bootstrap/css/bootstrap.css.map
cosmicdb/static/cosmicdb/adminlte/bootstrap/css/bootstrap.min.css
cosmicdb/static/cosmicdb/adminlte/bootstrap/css/bootstrap.min.css.map
cosmicdb/static/cosmicdb/adminlte/bootstrap/fonts/glyphicons-halflings-regular.eot
cosmicdb/static/cosmicdb/adminlte/bootstrap/fonts/glyphicons-halflings-regular.svg
cosmicdb/static/cosmicdb/adminlte/bootstrap/fonts/glyphicons-halflings-regular.ttf
cosmicdb/static/cosmicdb/adminlte/bootstrap/fonts/glyphicons-halflings-regular.woff
cosmicdb/static/cosmicdb/adminlte/bootstrap/fonts/glyphicons-halflings-regular.woff2
cosmicdb/static/cosmicdb/adminlte/bootstrap/js/bootstrap.js
cosmicdb/static/cosmicdb/adminlte/bootstrap/js/bootstrap.min.js
cosmicdb/static/cosmicdb/adminlte/bootstrap/js/npm.js
cosmicdb/static/cosmicdb/adminlte/dist/css/AdminLTE.css
cosmicdb/static/cosmicdb/adminlte/dist/css/AdminLTE.min.css
cosmicdb-0.0.33.dist-info/LICENSE.txt
cosmicdb-0.0.33.dist-info/METADATA
cosmicdb-0.0.33.dist-info/WHEEL
cosmicdb-0.0.33.dist-info/top_level.txt
cosmicdb-0.0.33.dist-info/RECORD
